LyPeUtils/__init__.py
LyPeUtils/fix_dmp_files.py
LyPeUtils/pefile.py
LyPeUtils/peutils.py
LyPeUtils-1.0.0.dist-info/LICENSE
LyPeUtils-1.0.0.dist-info/METADATA
LyPeUtils-1.0.0.dist-info/WHEEL
LyPeUtils-1.0.0.dist-info/top_level.txt
LyPeUtils-1.0.0.dist-info/RECORD
