Metadata-Version: 2.1
Name: LyPeUtils
Version: 1.0.0
Summary: A powerful x64dbg remote debugging module tools
Home-page: UNKNOWN
Author: lyshark
Author-email: me@lyshark.com
License: MIT Licence
Platform: any
Requires-Python: >=3.6.0
Requires-Dist: pefile (<=2022.5.30)
